{
  "annotations": [
    {
      "start_time": 13,
      "end_time": 29,
      "annotation": [
        {
          "type": "paragraph",
          "children": [
            {
              "text": "Sound of footsteps, first presumably on the stairs and then walking across the floor"
            }
          ]
        }
      ],
      "tags": [
        {
          "category": "Sound Effects",
          "tag": "sound effects"
        }
      ],
      "uuid": "e4a3e0aa-a42d-4048-a7be-80486a30420f"
    },
    {
      "start_time": 102,
      "end_time": 102,
      "annotation": [
        {
          "type": "paragraph",
          "children": [
            {
              "text": "High-pitched groan"
            }
          ]
        }
      ],
      "tags": [
        {
          "category": "Sound Effects",
          "tag": "sound effects"
        }
      ],
      "uuid": "7c6765e0-8792-4b4a-90a3-9436c420acc3"
    },
    {
      "start_time": 111,
      "end_time": 112,
      "annotation": [
        {
          "type": "paragraph",
          "children": [
            {
              "text": "Man grunting"
            }
          ]
        }
      ],
      "tags": [
        {
          "category": "Sound Effects",
          "tag": "sound effects"
        }
      ],
      "uuid": "de15fd2b-aed3-4832-ae5d-90e3e95093ab"
    },
    {
      "start_time": 118,
      "end_time": 118,
      "annotation": [
        {
          "type": "paragraph",
          "children": [
            {
              "text": "Faint splashing, indicating a the body hitting liquid concrete"
            }
          ]
        }
      ],
      "tags": [
        {
          "category": "Sound Effects",
          "tag": "sound effects"
        }
      ],
      "uuid": "fae8a148-565e-4e1e-93b3-89df60a73613"
    },
    {
      "start_time": 125,
      "end_time": 133,
      "annotation": [
        {
          "type": "paragraph",
          "children": [
            {
              "text": "Sound of bubbling, indicating the body sinking"
            }
          ]
        }
      ],
      "tags": [
        {
          "category": "Sound Effects",
          "tag": "sound effects"
        }
      ],
      "uuid": "5b27e46f-ee9b-4c77-a98d-d05a715d216a"
    }
  ],
  "set": "Default",
  "event_id": "2c8107c5-26de-46d9-8ed0-e39fe4a8c68c",
  "source_id": "2da0d3f3-6cec-4023-b8f5-d0f769a62aca"
}